{"data":[{"code":"ART241106072681MZBR","origin_url":"https://www.phnompenhpost.com/sport/finswimmers-host-asean-champs-team-kicks-to-podium-finish","site_code":"KH02","url":null,"image":"https://github.com/user-attachments/assets/227ba76f-d243-44a3-9450-48e955674b07","title":"​Finswimmers host ASEAN champs; team kicks to podium finish​","description":"​​Finswimmers host ASEAN champs; team kicks to podium finish​","status":"FINISH_META","category_code":"SPORT","language_code":"en","tags":null},{"code":"ART241104081668VMVT","origin_url":"https://www.phnompenhpost.com/sport/cpl-update-phnom-penh-crown-extends-streak-boeung-ket-coach-says-not-a-miracle-worker-","site_code":"KH02","url":null,"image":"https://github.com/user-attachments/assets/922f197d-4386-4088-b480-7f34675dc640","title":"​CPL update: Phnom Penh Crown extends streak; Boeung Ket coach says ‘not a miracle worker’​","description":"​​CPL update: Phnom Penh Crown extends streak; Boeung Ket coach says ‘not a miracle worker’​","status":"FINISH_META","category_code":"SPORT","language_code":"en","tags":null},{"code":"ART241101104617HPH0","origin_url":"https://www.phnompenhpost.com/sport/futsal-team-looking-for-upsets-at-asean-champs","site_code":"KH02","url":null,"image":"https://github.com/user-attachments/assets/b854f3b7-dddc-422f-ad39-b51d3700678c","title":"​Futsal team looking for upsets at ASEAN Champs​","description":"​​Futsal team looking for upsets at ASEAN Champs​","status":"FINISH_META","category_code":"SPORT","language_code":"en","tags":null},{"code":"ART2410310656SOTS56","origin_url":"https://www.phnompenhpost.com/sport/manet-national-games-a-celebration-of-pride","site_code":"KH02","url":null,"image":"https://github.com/user-attachments/assets/6e4e75a0-3379-4e00-857a-1ebc6943b3b4","title":"​Manet: National Games a celebration of pride​","description":"​​Manet: National Games a celebration of pride​","status":"FINISH_META","category_code":"SPORT","language_code":"en","tags":null},{"code":"ART2410301132K3MFIT","origin_url":"https://www.phnompenhpost.com/sport/chilled-out-svay-rieng-secure-afc-knockout-spot-with-victory-in-7-degree-encounter","site_code":"KH02","url":null,"image":"https://pppenglish.sgp1.digitaloceanspaces.com/image/main/202410/30_10_2024_mm.jpg","title":"​Chilled out Svay Rieng secure AFC knockout spot with victory in 7 degree encounter​","description":"​​Chilled out Svay Rieng secure AFC knockout spot with victory in 7 degree encounter​","status":"FINISH_META","category_code":"SPORT","language_code":"en","tags":null},{"code":"ART2410300401WATG10","origin_url":"https://www.phnompenhpost.com/sport/svay-rieng-gear-up-for-cool-challenge-against-mongolian-champs","site_code":"KH02","url":null,"image":"https://github.com/user-attachments/assets/88191b79-3951-4d99-a846-92449d932bf6","title":"​Svay Rieng gear up for cool challenge against Mongolian champs​","description":"​​Svay Rieng gear up for cool challenge against Mongolian champs​","status":"FINISH_META","category_code":"SPORT","language_code":"en","tags":null},{"code":"ART2410280826Q670PK","origin_url":"https://www.phnompenhpost.com/sport/young-kouprey-cup-qualifier-dreams-shattered","site_code":"KH02","url":null,"image":"https://github.com/user-attachments/assets/d90bcde0-b557-4a2a-a12f-83e8c47abfe9","title":"​Young Kouprey cup qualifier dreams shattered​","description":"​​Young Kouprey cup qualifier dreams shattered​","status":"FINISH_META","category_code":"SPORT","language_code":"en","tags":null},{"code":"ART2410240627XXFUT2","origin_url":"https://www.phnompenhpost.com/sport/second-chances-thin-on-ground-as-cpl-clubs-face-varied-fortunes","site_code":"KH02","url":null,"image":"https://github.com/user-attachments/assets/83a1f9d5-7a34-4d9b-8045-c64b69581c36","title":"​Second chances thin on ground as CPL clubs face varied fortunes​","description":"​​Second chances thin on ground as CPL clubs face varied fortunes​","status":"FINISH_META","category_code":"SPORT","language_code":"en","tags":null},{"code":"ART2410231101P86LC6","origin_url":"https://www.phnompenhpost.com/sport/volleyball-legend-channaro-retires-federation-aim-to-keep-him-close","site_code":"KH02","url":null,"image":"https://github.com/user-attachments/assets/b5c3a610-3032-467d-91ff-29339eeb7770","title":"​Volleyball legend Channaro retires, federation aim to keep him close​","description":"​​Volleyball legend Channaro retires, federation aim to keep him close​","status":"FINISH_META","category_code":"SPORT","language_code":"en","tags":null},{"code":"ART241022070160R2HB","origin_url":"https://www.phnompenhpost.com/sport/u17-macau-victory-marred-by-criticism-from-coach","site_code":"KH02","url":null,"image":"https://github.com/user-attachments/assets/3107057e-16eb-44ce-aa23-f38e724d4aed","title":"​U17 Macau victory marred by criticism from coach​","description":"​​U17 Macau victory marred by criticism from coach​","status":"FINISH_META","category_code":"SPORT","language_code":"en","tags":null},{"code":"ART2410210856AA2C2I","origin_url":"https://www.phnompenhpost.com/sport/crown-edge-svay-rieng-in-thrilling-4-3-encounter","site_code":"KH02","url":null,"image":"https://github.com/user-attachments/assets/eb1b318b-ecdb-44e5-97eb-4e5d83385b8f","title":"​Crown edge Svay Rieng in thrilling 4-3 encounter​","description":"​​Crown edge Svay Rieng in thrilling 4-3 encounter​","status":"FINISH_META","category_code":"SPORT","language_code":"en","tags":null},{"code":"ART24102106561CFPL1","origin_url":"https://www.phnompenhpost.com/sport/manet-we-must-unify-to-preserve-promote-traditional-martial-arts","site_code":"KH02","url":null,"image":"https://github.com/user-attachments/assets/32e813bd-4e3f-4cfa-9f77-635b9b808b17","title":"​Manet: We must unify to preserve, promote traditional martial arts​","description":"​​Manet: We must unify to preserve, promote traditional martial arts​","status":"FINISH_META","category_code":"SPORT","language_code":"en","tags":null},{"code":"ART2410171545YN9CNB","origin_url":"https://www.phnompenhpost.com/national/new-national-football-coach-outlines-goals-for-tonight-s-chinese-taipei-friendly","site_code":"KH02","url":null,"image":"https://github.com/user-attachments/assets/fcb8d200-bd97-4f83-a981-2c3e94271ef1","title":"​New national football coach outlines goals for tonight’s Chinese Taipei friendly​","description":"​​New national football coach outlines goals for tonight’s Chinese Taipei friendly​","status":"FINISH_META","category_code":"SPORT","language_code":"en","tags":null},{"code":"ART2410171545W72ZY2","origin_url":"https://www.phnompenhpost.com/sport/wrestlers-set-high-hopes-for-asean-championship-concerns-loom-for-sea-games","site_code":"KH02","url":null,"image":"https://github.com/user-attachments/assets/366e7392-2d1d-4624-964f-8215a32996cf","title":"​Wrestlers set high hopes for ASEAN Championship; Concerns loom for SEA Games​","description":"​​Wrestlers set high hopes for ASEAN Championship; Concerns loom for SEA Games​","status":"FINISH_META","category_code":"SPORT","language_code":"en","tags":null},{"code":"ART2410171545QQ0KM9","origin_url":"https://www.phnompenhpost.com/sport/kingdom-makes-history-at-asian-kickboxing-champs-4th-on-medal-table","site_code":"KH02","url":null,"image":"https://github.com/user-attachments/assets/68c467f5-326e-4a67-b444-67b1bac42b33","title":"​Kingdom makes history at Asian Kickboxing Champs, 4th on medal table​","description":"​​Kingdom makes history at Asian Kickboxing Champs, 4th on medal table​","status":"FINISH_META","category_code":"SPORT","language_code":"en","tags":null},{"code":"ART24101715456EVZ8F","origin_url":"https://www.phnompenhpost.com/sport/new-coach-looks-to-build-on-momentum-as-kouprey-take-on-hong-kong-tonight","site_code":"KH02","url":null,"image":"https://github.com/user-attachments/assets/78cfa0ed-c637-4008-b46c-a92c1aab7f01","title":"​New coach looks to build on momentum as Kouprey take on Hong Kong tonight​","description":"​​New coach looks to build on momentum as Kouprey take on Hong Kong tonight​","status":"FINISH_META","category_code":"SPORT","language_code":"en","tags":null},{"code":"ART24101715452B2035","origin_url":"https://www.phnompenhpost.com/sport/water-jet-team-stun-world-with-record-world-series-medal-haul","site_code":"KH02","url":null,"image":"https://github.com/user-attachments/assets/db3a3b1f-a0b5-4c77-8842-41e51cd60fbc","title":"​Water jet team stun world with record World Series medal haul​","description":"​​Water jet team stun world with record World Series medal haul​","status":"FINISH_META","category_code":"SPORT","language_code":"en","tags":null}],"prev":null,"next":null}